{
  "title": "Como captar multitudes para escuchar el Evangelio",
  "slug": "como-captar-multitudes-para-escuchar-el-evangelio",
  "category": "Reflexão",
  "shortDescription": "Este libro fue creado para ayudar a iglesias, ministerios, líderes, jóvenes y equipos de evangelismo a usar el teatro como una herramienta poderosa para comunicar el mensaje de Dios de una manera clara, creativa y profunda.",
  "summary": "Este material aborda el uso del teatro en la calle, en eventos evangelísticos y también dentro de la iglesia, mostrando cómo una obra puede ayudar a reflexionar sobre temas como la falta de perdón, el orgullo, la murmuración, la indiferencia, la división, el desánimo, los conflictos familiares, la falta de compromiso y otras realidades que muchas veces necesitan ser tratadas con sabiduría espiritual.\n\nTambién encontrarás orientación sobre cómo preparar obras visuales, mímicas y gestuales, especialmente útiles para evangelismo de calle, donde no siempre es posible depender de diálogos hablados. A través de música, gestos, efectos de sonido, voces grabadas y expresión corporal, el mensaje puede llegar con fuerza aun en lugares abiertos y con mucho movimiento.",
  "price": "30",
  "coverImage": "/books/Como-Captar-Multitudes.jpeg",
  "hotmartUrl": "https://go.hotmart.com/D106595034O",
  "language": "Español",
  "format": "PDF",
  "pages": 45,
  "active": true,
  "createdAt": "2026-07-02T22:09:28.278Z"
}